kerassurgeon/__init__.py
kerassurgeon/_utils/__init__.py
kerassurgeon/_utils/layer.py
kerassurgeon/_utils/node.py
kerassurgeon/_utils/tensor_dict.py
kerassurgeon/examples/__init__.py
kerassurgeon/examples/inception_flowers_prune.py
kerassurgeon/examples/inception_flowers_tune.py
kerassurgeon/examples/lenet_mnist.py
kerassurgeon/identify.py
kerassurgeon/operations.py
kerassurgeon/surgeon.py
kerassurgeon/utils.py
kerassurgeon-0.2.0.dist-info/LICENSE
kerassurgeon-0.2.0.dist-info/WHEEL
kerassurgeon-0.2.0.dist-info/METADATA
kerassurgeon-0.2.0.dist-info/RECORD
